{"id":"medusa-submarine-cable-system","name":"Medusa Submarine Cable System","length":"8,760 km","landing_points":[{"id":"algiers-algeria","name":"Algiers, Algeria","country":"Algeria","is_tbd":null},{"id":"collo-algeria","name":"Collo, Algeria","country":"Algeria","is_tbd":null},{"id":"yeroskipos-cyprus","name":"Yeroskipos, Cyprus","country":"Cyprus","is_tbd":null},{"id":"port-said-egypt","name":"Port Said, Egypt","country":"Egypt","is_tbd":null},{"id":"marseille-france","name":"Marseille, France","country":"France","is_tbd":null},{"id":"heraklion-greece","name":"Heraklion, Greece","country":"Greece","is_tbd":null},{"id":"mazara-del-vallo-italy","name":"Mazara del Vallo, Italy","country":"Italy","is_tbd":null},{"id":"benghazi-libya","name":"Benghazi, Libya","country":"Libya","is_tbd":null},{"id":"tripoli-libya","name":"Tripoli, Libya","country":"Libya","is_tbd":null},{"id":"nador-morocco","name":"Nador, Morocco","country":"Morocco","is_tbd":null},{"id":"ttouan-morocco","name":"Tétouan, Morocco","country":"Morocco","is_tbd":null},{"id":"carcavelos-portugal","name":"Carcavelos, Portugal","country":"Portugal","is_tbd":null},{"id":"sines-portugal","name":"Sines, Portugal","country":"Portugal","is_tbd":null},{"id":"barcelona-spain","name":"Barcelona, Spain","country":"Spain","is_tbd":null},{"id":"torreguadiaro-spain","name":"Torreguadiaro, Spain","country":"Spain","is_tbd":null},{"id":"zahara-de-los-atunes-spain","name":"Zahara de los Atunes, Spain","country":"Spain","is_tbd":null},{"id":"bizerte-tunisia","name":"Bizerte, Tunisia","country":"Tunisia","is_tbd":null}],"owners":"AFRIX Telecom","suppliers":"ASN","rfs":"2025 Q4","rfs_year":2025,"is_planned":true,"url":"https://medusascs.com/","notes":null}
